zensols/spanmatch/__init__.py
zensols/spanmatch/app.py
zensols/spanmatch/cli.py
zensols/spanmatch/domain.py
zensols/spanmatch/match.py
zensols/spanmatch/resources/app.conf
zensols/spanmatch/resources/hyperparam.yml
zensols/spanmatch/resources/obj.yml
zensols.spanmatch-0.0.1.dist-info/METADATA
zensols.spanmatch-0.0.1.dist-info/WHEEL
zensols.spanmatch-0.0.1.dist-info/entry_points.txt
zensols.spanmatch-0.0.1.dist-info/top_level.txt
zensols.spanmatch-0.0.1.dist-info/RECORD
