Metadata-Version: 2.1
Name: zensols.spanmatch
Version: 0.0.1
Summary: An API to match spans of semantically similar text across documents.
Home-page: https://github.com/plandes/spanmatch
Download-URL: https://github.com/plandes/spanmatch/releases/download/v0.0.1/zensols.spanmatch-0.0.1-py3-none-any.whl
Author: Paul Landes
Author-email: landes@mailc.net
Keywords: tooling
Requires-Dist: POT (~=0.8.2)
Requires-Dist: zensols.deepnlp (~=1.9.0)
Requires-Dist: zensols.datdesc (~=0.0.2)
